{
  "recentFiles": [
    {
      "basename": "6 - Mutators & Casts",
      "path": "6 - Laravel/18 - Eloquent ORM/1 - Eloquent'a Başlarken/6 - Mutators & Casts.md"
    },
    {
      "basename": "5 - Collections",
      "path": "6 - Laravel/18 - Eloquent ORM/1 - Eloquent'a Başlarken/5 - Collections.md"
    },
    {
      "basename": "4 - Modelleri Sorgulama ve Karşılaştırma",
      "path": "6 - Laravel/18 - Eloquent ORM/1 - Eloquent'a Başlarken/4 - Modelleri Sorgulama ve Karşılaştırma.md"
    },
    {
      "basename": "7 - Getting Started",
      "path": "6 - Laravel/18 - Eloquent ORM/1 - Eloquent'a Başlarken/7 - Getting Started.md"
    },
    {
      "basename": "6 - Relationships",
      "path": "6 - Laravel/18 - Eloquent ORM/2 - Relationships (İlişkiler)/6 - Relationships.md"
    },
    {
      "basename": "3 - Modelleri Budama ve Kopyalama",
      "path": "6 - Laravel/18 - Eloquent ORM/1 - Eloquent'a Başlarken/3 - Modelleri Budama ve Kopyalama.md"
    },
    {
      "basename": "2 - Modellerin Çağrılması ve Yönetilmesi",
      "path": "6 - Laravel/18 - Eloquent ORM/1 - Eloquent'a Başlarken/2 - Modellerin Çağrılması ve Yönetilmesi.md"
    },
    {
      "basename": "1 - Eloquent Basics",
      "path": "6 - Laravel/18 - Eloquent ORM/1 - Eloquent'a Başlarken/1 - Eloquent Basics.md"
    },
    {
      "basename": "1 - Relationships Basics",
      "path": "6 - Laravel/18 - Eloquent ORM/2 - Relationships (İlişkiler)/1 - Relationships Basics.md"
    },
    {
      "basename": "5 - İlgili Modelleri Oluşturma ve Güncelleme",
      "path": "6 - Laravel/18 - Eloquent ORM/2 - Relationships (İlişkiler)/5 - İlgili Modelleri Oluşturma ve Güncelleme.md"
    },
    {
      "basename": "4 - Eager Loading",
      "path": "6 - Laravel/18 - Eloquent ORM/2 - Relationships (İlişkiler)/4 - Eager Loading.md"
    },
    {
      "basename": "3 - İlişkileri Sorgulama",
      "path": "6 - Laravel/18 - Eloquent ORM/2 - Relationships (İlişkiler)/3 - İlişkileri Sorgulama.md"
    },
    {
      "basename": "2 - Poliformik ve Dinamik İlişkiler",
      "path": "6 - Laravel/18 - Eloquent ORM/2 - Relationships (İlişkiler)/2 - Poliformik ve Dinamik İlişkiler.md"
    },
    {
      "basename": "2- PHP Echo-Print",
      "path": "1- PHP'ye Giriş/2- PHP Echo-Print.md"
    },
    {
      "basename": "1- Başlarken",
      "path": "1- PHP'ye Giriş/1- Başlarken.md"
    },
    {
      "basename": "3 - Controllers",
      "path": "6 - Laravel/4 - Controllers/3 - Controllers.md"
    },
    {
      "basename": "9 - Facades",
      "path": "5- Laravele Giriş/9 - Facades.md"
    },
    {
      "basename": "8 - Service Providers",
      "path": "5- Laravele Giriş/8 - Service Providers.md"
    },
    {
      "basename": "7 - Service Container",
      "path": "5- Laravele Giriş/7 - Service Container.md"
    },
    {
      "basename": "4 - Bir İsteğin Yaşam Döngüsü",
      "path": "5- Laravele Giriş/4 - Bir İsteğin Yaşam Döngüsü.md"
    },
    {
      "basename": "1 - Views",
      "path": "6 - Laravel/6 - Views/1 - Views.md"
    },
    {
      "basename": "1 - Seeding",
      "path": "6 - Laravel/17 - Seeding/1 - Seeding.md"
    },
    {
      "basename": "1 - Migrations",
      "path": "6 - Laravel/16 - Migrations/1 - Migrations.md"
    },
    {
      "basename": "1 - Koleksiyonlar",
      "path": "6 - Laravel/12 - Collections/1 - Koleksiyonlar.md"
    },
    {
      "basename": "3 - HTTP Sessions",
      "path": "6 - Laravel/5 - Requests & Respones & Session/3 - HTTP Sessions.md"
    },
    {
      "basename": "2 - HTTP Respones (Yanıtlar)",
      "path": "6 - Laravel/5 - Requests & Respones & Session/2 - HTTP Respones (Yanıtlar).md"
    },
    {
      "basename": "1 - HTTP Requests (İstekler)",
      "path": "6 - Laravel/5 - Requests & Respones & Session/1 - HTTP Requests (İstekler).md"
    },
    {
      "basename": "3 - Middleware",
      "path": "6 - Laravel/2 - Middleware/3 - Middleware.md"
    },
    {
      "basename": "1 - Middleware Temelleri",
      "path": "6 - Laravel/2 - Middleware/1 - Middleware Temelleri.md"
    },
    {
      "basename": "4 - Routing",
      "path": "6 - Laravel/1 - Routing/4 - Routing.md"
    },
    {
      "basename": "3 - Rotalara Erişme, Düzenleme ve Cachleme",
      "path": "6 - Laravel/1 - Routing/3 - Rotalara Erişme, Düzenleme ve Cachleme.md"
    },
    {
      "basename": "1 - Routing Temelleri",
      "path": "6 - Laravel/1 - Routing/1 - Routing Temelleri.md"
    },
    {
      "basename": "5 - Dizin Yapısı",
      "path": "5- Laravele Giriş/5 - Dizin Yapısı.md"
    },
    {
      "basename": "2 - Laravel Kurulumu",
      "path": "5- Laravele Giriş/2 - Laravel Kurulumu.md"
    },
    {
      "basename": "1 - Laravel’e Başlamadan Önce",
      "path": "5- Laravele Giriş/1 - Laravel’e Başlamadan Önce.md"
    },
    {
      "basename": "2 - Tablo Oluşturma",
      "path": "6 - Laravel/16 - Migrations/2 - Tablo Oluşturma.md"
    },
    {
      "basename": "6 - Frontend",
      "path": "5- Laravele Giriş/6 - Frontend.md"
    },
    {
      "basename": "1 - Hata Yakalama",
      "path": "6 - Laravel/11 - Error Handling/1 - Hata Yakalama.md"
    },
    {
      "basename": "7 - Blade Şablonları (Bütün Konu)",
      "path": "6 - Laravel/8 - Blade Templates/7 - Blade Şablonları (Bütün Konu).md"
    },
    {
      "basename": "3 - Bileşenler",
      "path": "6 - Laravel/8 - Blade Templates/3 - Bileşenler.md"
    },
    {
      "basename": "1 - Validation (Doğrulama)",
      "path": "6 - Laravel/10 - Validation/1 - Validation (Doğrulama).md"
    },
    {
      "basename": "6 - Stacks (Yığınlar)",
      "path": "6 - Laravel/8 - Blade Templates/6 - Stacks (Yığınlar).md"
    },
    {
      "basename": "2 - Blade Yönergeleri",
      "path": "6 - Laravel/8 - Blade Templates/2 - Blade Yönergeleri.md"
    },
    {
      "basename": "1 - URL Oluşturma",
      "path": "6 - Laravel/9 - URL Generation/1 - URL Oluşturma.md"
    },
    {
      "basename": "12 - Breeze",
      "path": "6 - Laravel/U - Breeze/12 - Breeze.md"
    },
    {
      "basename": "7- PHP Strings (Dizeler)",
      "path": "1- PHP'ye Giriş/7- PHP Strings (Dizeler).md"
    },
    {
      "basename": "5 - Formlar",
      "path": "6 - Laravel/8 - Blade Templates/5 - Formlar.md"
    },
    {
      "basename": "4 - Şablon Oluşturma",
      "path": "6 - Laravel/8 - Blade Templates/4 - Şablon Oluşturma.md"
    },
    {
      "basename": "1 - Blade Şablonlarına Giriş",
      "path": "6 - Laravel/8 - Blade Templates/1 - Blade Şablonlarına Giriş.md"
    },
    {
      "basename": "5- PHP Data Types (Veri Türleri)",
      "path": "1- PHP'ye Giriş/5- PHP Data Types (Veri Türleri).md"
    }
  ],
  "omittedPaths": [],
  "maxLength": null,
  "openType": "tab"
}